apollopayment_api/__init__.py
apollopayment_api/error.py
apollopayment_api/domains/__init__.py
apollopayment_api/domains/address_book/__init__.py
apollopayment_api/domains/advanced_account/__init__.py
apollopayment_api/domains/auto_swaps/__init__.py
apollopayment_api/domains/basic_actions/__init__.py
apollopayment_api/domains/blockchain_addresses/__init__.py
apollopayment_api/domains/crosschain_bridge/__init__.py
apollopayment_api/domains/crosschain_swaps/__init__.py
apollopayment_api/domains/invoices/__init__.py
apollopayment_api/domains/kyt/__init__.py
apollopayment_api/domains/orders/__init__.py
apollopayment_api/domains/orphan_transactions/__init__.py
apollopayment_api/domains/partners_api/__init__.py
apollopayment_api/domains/personal_addresses/__init__.py
apollopayment_api/domains/recurring_payments/__init__.py
apollopayment_api/domains/webhooks/__init__.py
apollopayment_api/domains/withdraws/__init__.py
apollopayment_api/resources/__init__.py
apollopayment_api/resources/constants.py
apollopayment_api/resources/requester.py
apollopayment_api/resources/response.py
apollopayment_api/resources/utils.py
apollopayment_api-0.0.8.dist-info/LICENSE
apollopayment_api-0.0.8.dist-info/METADATA
apollopayment_api-0.0.8.dist-info/WHEEL
apollopayment_api-0.0.8.dist-info/top_level.txt
apollopayment_api-0.0.8.dist-info/RECORD
