Metadata-Version: 2.1
Name: apollopayment-api
Version: 0.0.8
Summary: SDK for Apollopayment API
Home-page: https://github.com/apollopayment/python_sdk
Author: Apollopayment Team
Author-email: support@apollopayment.io
License: UNKNOWN
Project-URL: Bug Tracker, https://github.com/apollopayment/python_sdk/issues
Platform: UNKNOWN
Classifier: Programming Language :: Python :: 3
Classifier: License :: OSI Approved :: BSD License
Classifier: Operating System :: OS Independent
Requires-Python: >=3.6
License-File: LICENSE
Requires-Dist: requests >=2.28.0
